scripts/__init__.py
scripts/example.py
n2k/__init__.py
n2k/logger.py
n2k/utils.py
n2k_decode-0.1.0.dist-info/METADATA
n2k_decode-0.1.0.dist-info/WHEEL
n2k_decode-0.1.0.dist-info/entry_points.txt
n2k_decode-0.1.0.dist-info/RECORD
