Metadata-Version: 2.4
Name: n2k-decode
Version: 0.1.0
Summary: N2K module for handling NMEA 2000 data
Project-URL: Homepage, https://gitlab.com/cedricmaigrot/n2k
Project-URL: Documentation, https://gitlab.com/cedricmaigrot/n2k#readme
Project-URL: Bug-Tracker, https://gitlab.com/cedricmaigrot/n2k/-/issues
Project-URL: Source, https://gitlab.com/cedricmaigrot/n2k
Author-email: Cédric Maigrot <cedric.maigrot@example.com>
Maintainer-email: Cédric Maigrot <cedric.maigrot@example.com>
License-Expression: MIT
Keywords: can,maritime,n2k,navigation,nmea
Classifier: Development Status :: 4 - Beta
Classifier: Intended Audience :: Developers
Classifier: License :: OSI Approved :: MIT License
Classifier: Programming Language :: Python :: 3
Classifier: Programming Language :: Python :: 3.12
Classifier: Topic :: Scientific/Engineering :: GIS
Classifier: Topic :: Software Development :: Libraries :: Python Modules
Requires-Python: >=3.12
Requires-Dist: black>=25.1.0
Requires-Dist: folium>=0.19.5
Requires-Dist: marulc>=0.2.0
Requires-Dist: openpyxl>=3.1.5
Requires-Dist: pandas>=2.2.3
Requires-Dist: pyyaml>=6.0.2
Requires-Dist: tomli>=2.2.1
Requires-Dist: tqdm>=4.67.1
